keycloak_oauth/__init__.py
keycloak_oauth/starlette_admin.py
keycloak_oauth-0.3.0.dist-info/LICENSE
keycloak_oauth-0.3.0.dist-info/METADATA
keycloak_oauth-0.3.0.dist-info/WHEEL
keycloak_oauth-0.3.0.dist-info/RECORD
