Metadata-Version: 2.1
Name: keycloak-oauth
Version: 0.3.0
Summary: Keycloak OAuth client for Python projects
Home-page: https://github.com/bakdata/python-keycloak-oauth
License: MIT
Author: bakdata
Author-email: opensource@bakdata.com
Requires-Python: >=3.10,<4.0
Classifier: License :: OSI Approved :: MIT License
Classifier: Programming Language :: Python :: 3
Classifier: Programming Language :: Python :: 3.10
Classifier: Programming Language :: Python :: 3.11
Classifier: Programming Language :: Python :: 3.12
Provides-Extra: fastapi
Provides-Extra: starlette-admin
Requires-Dist: authlib (>=1.3.0,<2.0.0)
Requires-Dist: fastapi (>=0.104.1,<0.105.0) ; extra == "fastapi"
Requires-Dist: httpx (>=0.26.0,<0.27.0)
Requires-Dist: itsdangerous (>=2.1.2,<3.0.0)
Requires-Dist: pydantic[email] (>=2.4.2,<3.0.0)
Requires-Dist: starlette (>=0.27.0,<0.28.0)
Requires-Dist: starlette-admin (>=0.13.2,<0.14.0) ; extra == "starlette-admin"
Project-URL: Repository, https://github.com/bakdata/python-keycloak-oauth
